dummy_package/__init__.py
dummy_package/dummy.py
dummy_project_pypituf-0.0.1.dist-info/METADATA
dummy_project_pypituf-0.0.1.dist-info/WHEEL
dummy_project_pypituf-0.0.1.dist-info/top_level.txt
dummy_project_pypituf-0.0.1.dist-info/RECORD
