Metadata-Version: 2.1
Name: dummy-project-pypituf
Version: 0.0.1
Summary: A dummy project for testing PyPI
Home-page: https://github.com/yourusername/dummy_project
Author: Your Name
Author-email: your.email@example.com
License: UNKNOWN
Platform: UNKNOWN
Classifier: Programming Language :: Python :: 3
Classifier: License :: OSI Approved :: MIT License
Classifier: Operating System :: OS Independent
Requires-Python: >=3.6
